{
	"id": 138083218,
	"master_id": 138083218,
	"sku": "1898971129438",
	"name": "Đồ Chơi Xếp Hình MyndToys - My First Learning (Cho Bé Từ 2.5 Tuổi - Nhiều Chủ Đề)",
	"url_key": "do-choi-xep-hinh-myndtoys-my-first-learning-cho-be-tu-2-5-tuoi-nhieu-chu-de-p138083218",
	"url_path": "do-choi-xep-hinh-myndtoys-my-first-learning-cho-be-tu-2-5-tuoi-nhieu-chu-de-p138083218.html",
	"short_url": "https://tiki.vn/product-p138083218.html",
	"type": "configurable",
	"book_cover": null,
	"short_description": "Đồ Chơi Xếp Hình MyndToys - My First Learning (Cho Bé Từ 2.5 Tuổi - Nhiều Chủ Đề) BỘ SẢN PHẨM BAO GỒM:Hộp chữ nhật: 15 x 20 x 5 (cm) có nắp đậyBộ thẻ: 6 bảng ghép puzzle cỡ 14 x 20 cm tương ứng v...",
	"price": 268000,
	"list_price": 268000,
	"original_price": 268000,
	"badges": [
		{
			"code": "new_pdp",
			"text": "v1"
		}
	],
	"badges_new": [],
	"badges_v3": null,
	"tracking_info": null,
	"discount": 0,
	"discount_rate": 0,
	"rating_average": 5,
	"review_count": 4,
	"review_text": "(4)",
	"favourite_count": 0,
	"thumbnail_url": "https://salt.tikicdn.com/cache/280x280/ts/product/56/84/00/255732b1e617a2e5076c667a9518a3d8.jpg",
	"has_ebook": false,
	"inventory_status": "out_of_stock",
	"inventory_type": "backorder",
	"productset_group_name": "",
	"is_fresh": false,
	"seller": null,
	"is_flower": false,
	"is_gift_card": false,
	"salable_type": null,
	"data_version": 3300,
	"day_ago_created": 1572,
	"meta_title": "",
	"meta_description": "",
	"meta_keywords": "",
	"is_baby_milk": false,
	"is_acoholic_drink": false,
	"description": "<p><strong>Đồ Chơi Xếp Hình MyndToys </strong><strong>- </strong><strong>My First Learning </strong><strong>(</strong><strong>Cho Bé Từ 2.5 Tuổi </strong><strong>- </strong><strong>Nhiều Chủ Đề</strong><strong>)</strong></p>\n<p> </p>\n<p><strong>BỘ SẢN PHẨM BAO GỒM:</strong></p>\n<ul>\n<li>Hộp chữ nhật: 15 x 20 x 5 (cm) có nắp đậy</li>\n<li>Bộ thẻ: 6 bảng ghép puzzle cỡ 14 x 20 cm tương ứng với 24 miếng ghép puzzle về các chủ đề khác nhau.</li>\n<li>Kích thước thẻ: 7×10 (cm)</li>\n<li>Sticker thưởng</li>\n<li>Hướng dẫn cho phụ huynh</li>\n<li>Có 2 bộ sản phẩm thuộc dòng My First Learning cho các bé lựa chọn:</li>\n</ul>\n<ol>\n<li style=\"list-style-type: none;\">\n<ol>\n<li>Bộ sản phẩm My First Learning – Me &amp; My Family về chủ đề Bản thân và Gia đình</li>\n<li>Bộ sản phẩm My First Learning – World of Animals về chủ đề Thế giới động vật</li>\n</ol>\n</li>\n</ol>\n<p><strong>THÔNG TIN VỀ SẢN PHẨM:</strong></p>\n<ul>\n<li>Thương hiệu: MyndToys Singapore</li>\n<li>Sản xuất: Tại Việt Nam</li>\n<li>Độ tuổi: 2.5+</li>\n<li>Tiêu chuẩn an toàn: CPSIA, ASTM và CE.</li>\n<li>Dòng sản phẩm My First Learning gồm nhiều bộ sản phẩm với các chủ đề khác nhau để phù hợp với các sở thích của bé:</li>\n</ul>\n<ol>\n<li style=\"list-style-type: none;\">\n<ol>\n<li>My First Learning – Me &amp; My Family giúp trẻ tìm hiểu về bản thân và gia đình với 6 chủ đề đa dạng tương ứng với 6 bảng ghép puzzle.</li>\n<li>My First Learning – Me &amp; My Family giúp trẻ tìm hiểu về thế giới động vật với đa dạng 6 chủ đề tương ứng với 6 bảng ghép puzzle</li>\n</ol>\n</li>\n</ol>\n<ul>\n<li>Trò chơi kết hợp giữa tương tác hỏi đáp và ghép tranh puzzle, phát triển kỹ năng phối hợp tay mắt, kỹ năng nhận biết và tư duy logic.</li>\n<li>Tăng khả năng phản xạ và sự hứng thú khi tương tác cùng cha mẹ hoặc trong đội nhóm.</li>\n</ul>\n<p><img src=\"https://salt.tikicdn.com/ts/tmp/4e/6e/03/7b1b22fdb53527542f31a9c70f885848.jpg\" alt=\"\" width=\"750\" height=\"750\" /></p>\n<p><img id=\"https://salt.tikicdn.com/ts/tmp/84/75/2b/f4c08c2812962865740405f7d0ff55c6.jpg\" title=\"\" src=\"https://salt.tikicdn.com/ts/tmp/84/75/2b/f4c08c2812962865740405f7d0ff55c6.jpg\" alt=\"\" width=\"383\" height=\"383\" />   <img id=\"https://salt.tikicdn.com/ts/tmp/99/ab/f8/9505fe4dc150c5f5a995cb3cdf9eb9c0.jpg\" title=\"\" src=\"https://salt.tikicdn.com/ts/tmp/99/ab/f8/9505fe4dc150c5f5a995cb3cdf9eb9c0.jpg\" alt=\"\" width=\"381\" height=\"381\" /></p>\n<p><img id=\"https://salt.tikicdn.com/ts/tmp/58/76/0a/17ba6e043e3d3f74b62abd740596c677.jpg\" title=\"\" src=\"https://salt.tikicdn.com/ts/tmp/58/76/0a/17ba6e043e3d3f74b62abd740596c677.jpg\" alt=\"\" width=\"385\" height=\"385\" />   <img id=\"https://salt.tikicdn.com/ts/tmp/92/bc/aa/580f2e2ba1e6ae6086de4f0b96ad9821.jpg\" title=\"\" src=\"https://salt.tikicdn.com/ts/tmp/92/bc/aa/580f2e2ba1e6ae6086de4f0b96ad9821.jpg\" alt=\"\" width=\"384\" height=\"384\" /></p>\n<p><img id=\"https://salt.tikicdn.com/ts/tmp/56/84/00/eb6b96dae9e55c8a89096bcc02517629.jpg\" title=\"\" src=\"https://salt.tikicdn.com/ts/tmp/56/84/00/eb6b96dae9e55c8a89096bcc02517629.jpg\" alt=\"\" width=\"386\" height=\"386\" />   <img id=\"https://salt.tikicdn.com/ts/tmp/21/3e/c1/2cfc14b9079760cbe6b6fdcee017175f.jpg\" title=\"\" src=\"https://salt.tikicdn.com/ts/tmp/21/3e/c1/2cfc14b9079760cbe6b6fdcee017175f.jpg\" alt=\"\" width=\"386\" height=\"386\" /></p>\n<p>MyndToys là thương hiệu đồ chơi giáo dục dành cho trẻ từ 0 đến 8 tuổi, được kết tinh từ tình yêu con trẻ và kinh nghiệm nhiều năm trong lĩnh vực giáo dục của nhóm các chuyên gia giáo dục đến từ Singapore.</p>\n<p>Thêm vào đó những sản phẩm của MyndToys được sản xuất tại Việt Nam với qui trình sản xuất và kiểm nghiệm nghiêm ngặt, tự tin sẽ mang đến các sản phẩm đồ chơi giáo dục đạt tiêu chuẩn an toàn quốc tế với giá thành phù hợp, đồng hành với các bậc phụ huynh góp phần nâng cao trí tuệ và thẩm mĩ của trẻ em Việt Nam.</p><p>Giá sản phẩm trên Tiki đã bao gồm thuế theo luật hiện hành. Bên cạnh đó, tuỳ vào loại sản phẩm, hình thức và địa chỉ giao hàng mà có thể phát sinh thêm chi phí khác như phí vận chuyển, phụ phí hàng cồng kềnh, thuế nhập khẩu (đối với đơn hàng giao từ nước ngoài có giá trị trên 1 triệu đồng).....</p>",
	"images": [
		{
			"base_url": "https://salt.tikicdn.com/media/catalog/product/f5/15/2228f38cf84d1b8451bb49e2c4537081.png",
			"is_gallery": true,
			"label": null,
			"large_url": "https://salt.tikicdn.com/cache/w1200/media/catalog/product/f5/15/2228f38cf84d1b8451bb49e2c4537081.png",
			"medium_url": "https://salt.tikicdn.com/cache/w300/media/catalog/product/f5/15/2228f38cf84d1b8451bb49e2c4537081.png",
			"position": null,
			"small_url": "https://salt.tikicdn.com/cache/200x280/media/catalog/product/f5/15/2228f38cf84d1b8451bb49e2c4537081.png",
			"thumbnail_url": "https://salt.tikicdn.com/cache/200x280/media/catalog/product/f5/15/2228f38cf84d1b8451bb49e2c4537081.png"
		}
	],
	"warranty_policy": null,
	"brand": {
		"id": 5134333,
		"name": "MyndToys",
		"slug": "myndtoys"
	},
	"current_seller": null,
	"other_sellers": [],
	"specifications": [],
	"product_links": [],
	"gift_item_title": "",
	"services_and_promotions": [],
	"promitions": [],
	"breadcrumbs": [
		{
			"url": "/do-choi-me-be/c2549",
			"name": "Đồ Chơi - Mẹ & Bé",
			"category_id": 2549
		},
		{
			"url": "/do-choi/c5250",
			"name": "Đồ chơi",
			"category_id": 5250
		},
		{
			"url": "/lap-ghep-xep-hinh/c1948",
			"name": "Lắp ghép, Xếp hình",
			"category_id": 1948
		},
		{
			"url": "https://tiki.vn/do-choi-xep-hinh-myndtoys-my-first-learning-cho-be-tu-2-5-tuoi-nhieu-chu-de-p138083218.html",
			"name": "Đồ Chơi Xếp Hình MyndToys - My First Learning (Cho Bé Từ 2.5 Tuổi - Nhiều Chủ Đề)",
			"category_id": 0
		}
	],
	"installment_info_v2": null,
	"is_seller_in_chat_whitelist": false,
	"inventory": {
		"product_virtual_type": null,
		"fulfillment_type": "dropship"
	},
	"warranty_info": null,
	"return_and_exchange_policy": "",
	"is_tier_pricing_available": false,
	"is_tier_pricing_eligible": false
}